dcs/__init__.py
dcs/_config/README.md
dcs/_config/abb_irb4600.json
dcs/_config/beckhoff_controller.json
dcs/data/__init__.py
dcs/data/processing.py
dcs/data/struct.py
dcs/hal/__init__.py
dcs/hal/device.py
dcs/hal/interface.py
dcs/hal/plc.py
dcs/infrastructure/__init__.py
dcs/infrastructure/config_manager.py
dcs/robot/__init__.py
dcs/robot/abb_config.py
dcs/robot/ros_client.py
dcs/utils/__init__.py
dcs/utils/data_processing.py
digital_casting_system-0.1.5.dist-info/METADATA
digital_casting_system-0.1.5.dist-info/WHEEL
digital_casting_system-0.1.5.dist-info/licenses/AUTHORS.md
digital_casting_system-0.1.5.dist-info/licenses/LICENSE
digital_casting_system-0.1.5.dist-info/RECORD
