Metadata-Version: 2.4
Name: digital_casting_system
Version: 0.1.5
Summary: A digital control package for Digital Control System
Project-URL: Changelog, https://github.com/USI-FMAA/digital_casting_system/blob/master/CHANGELOG.md
Project-URL: Documentation, https://usi-fmaa.github.io/digital_casting_system/
Project-URL: Homepage, https://usi-fmaa.github.io/digital_casting_system/
Project-URL: Issues, https://github.com/USI-FMAA/digital_casting_system/issues
Project-URL: Repository, https://github.com/USI-FMAA/digital_casting_system
Author-email: Wei-Ting Chen <chenwei@arch.ethz.ch>
License: MIT License
License-File: AUTHORS.md
License-File: LICENSE
Keywords: automation,concrete,digital casting,manufacturing,robotics
Classifier: Development Status :: 3 - Alpha
Classifier: Intended Audience :: Developers
Classifier: Intended Audience :: Science/Research
Classifier: License :: OSI Approved :: MIT License
Classifier: Operating System :: OS Independent
Classifier: Programming Language :: Python :: 3
Classifier: Programming Language :: Python :: 3.10
Classifier: Programming Language :: Python :: 3.11
Classifier: Programming Language :: Python :: 3.12
Classifier: Topic :: Scientific/Engineering
Classifier: Topic :: Software Development :: Libraries :: Python Modules
Requires-Python: >=3.10
Requires-Dist: attrs>=17.4
Requires-Dist: compas<=2.9.0
Requires-Dist: matplotlib>=3.8.4
Requires-Dist: numpy>=1.26
Requires-Dist: pandas>=2.2.0
Requires-Dist: pyads>=3.3.9
Requires-Dist: pydantic>=2.10.6
Requires-Dist: ruff>=0.8.2
Provides-Extra: dev
Requires-Dist: build>=1.3.0; extra == 'dev'
Requires-Dist: bump-my-version; extra == 'dev'
Requires-Dist: hatchling>=1.27.0; extra == 'dev'
Requires-Dist: invoke>=0.14; extra == 'dev'
Requires-Dist: pytest; extra == 'dev'
Requires-Dist: pytest-cov; extra == 'dev'
Requires-Dist: pytest-mock>=3.14.1; extra == 'dev'
Requires-Dist: ruff; extra == 'dev'
Requires-Dist: setuptools>=75.8.0; extra == 'dev'
Requires-Dist: twine; extra == 'dev'
Requires-Dist: wheel>=0.45.1; extra == 'dev'
Provides-Extra: docs
Requires-Dist: markdown; extra == 'docs'
Requires-Dist: markdown-exec; extra == 'docs'
Requires-Dist: mkdocs; extra == 'docs'
Requires-Dist: mkdocs-autorefs; extra == 'docs'
Requires-Dist: mkdocs-gen-files; extra == 'docs'
Requires-Dist: mkdocs-include-markdown-plugin; extra == 'docs'
Requires-Dist: mkdocs-literate-nav; extra == 'docs'
Requires-Dist: mkdocs-macros-plugin; extra == 'docs'
Requires-Dist: mkdocs-material>=9.1.15; extra == 'docs'
Requires-Dist: mkdocstrings-python; extra == 'docs'
Requires-Dist: pymdown-extensions>=10.14.3; extra == 'docs'
Provides-Extra: robot
